gsheet_access/__init__.py
gsheet_access-1.1.1.dist-info/LICENSE
gsheet_access-1.1.1.dist-info/METADATA
gsheet_access-1.1.1.dist-info/WHEEL
gsheet_access-1.1.1.dist-info/top_level.txt
gsheet_access-1.1.1.dist-info/RECORD
