Metadata-Version: 2.1
Name: gsheet-access
Version: 1.1.1
Summary: A Python package to read gsheet  from google drive using gsheet id and plot and save between two numerical axis.
Home-page: UNKNOWN
Author: Amreesh kumar
Author-email: starkk786@gmail.com
License: MIT
Platform: UNKNOWN
Classifier: License :: OSI Approved :: MIT License
Classifier: Programming Language :: Python :: 3
Classifier: Programming Language :: Python :: 3.7
Requires-Dist: pandas
Requires-Dist: numpy
Requires-Dist: gsheet
Requires-Dist: oauthclient
Requires-Dist: matplotlib
